html_to_json/__init__.py
html_to_json/convert_html.py
html_to_json/convert_html_tables.py
html_to_json-2.0.0.dist-info/LICENSE
html_to_json-2.0.0.dist-info/METADATA
html_to_json-2.0.0.dist-info/WHEEL
html_to_json-2.0.0.dist-info/top_level.txt
html_to_json-2.0.0.dist-info/zip-safe
html_to_json-2.0.0.dist-info/RECORD
