Metadata-Version: 2.1
Name: html_to_json
Version: 2.0.0
Summary: Convert html to json.
Home-page: https://github.com/fhightower/html-to-json
Author: Floyd Hightower
Author-email: 
License: MIT License
Project-URL: Documentation, https://github.com/fhightower/html-to-json
Project-URL: Say Thanks!, https://saythanks.io/to/floyd.hightower27%40gmail.com
Project-URL: Source, https://github.com/fhightower/html-to-json
Project-URL: Tracker, https://github.com/fhightower/html-to-json/issues
Project-URL: PyPi, https://pypi.org/project/html-to-json/
Project-URL: CI, https://travis-ci.com/fhightower/html-to-json.svg?branch=main
Project-URL: Changelog, https://github.com/fhightower/html-to-json/blob/main/CHANGELOG.md
Keywords: html to json,html,json,conversion
Platform: UNKNOWN
Classifier: Development Status :: 4 - Beta
Classifier: Intended Audience :: Developers
Classifier: Intended Audience :: Information Technology
Classifier: License :: OSI Approved :: MIT License
Classifier: Natural Language :: English
Classifier: Programming Language :: Python :: 3
Classifier: Programming Language :: Python :: 3.6
Classifier: Programming Language :: Python :: 3.7
Classifier: Programming Language :: Python :: 3.8
Classifier: Programming Language :: Python :: 3.9
